noframewin/__init__.py
noframewin/noframewin.py
noframewin-1.2.dist-info/LICENSE
noframewin-1.2.dist-info/METADATA
noframewin-1.2.dist-info/WHEEL
noframewin-1.2.dist-info/top_level.txt
noframewin-1.2.dist-info/RECORD
